<TRANS_CONF_1>
	<TRANS_COMMON_PARAMS>
		<MCU_TOKEN>2</MCU_TOKEN>
		<MCU_USER_TOKEN>2</MCU_USER_TOKEN>
		<MESSAGE_ID>424</MESSAGE_ID>
	</TRANS_COMMON_PARAMS>
	<ACTION>
		<SET_PARTY_VIDEO_LAYOUT_EX>
			<ID>1</ID>
			<PARTY_ID>1</PARTY_ID>
			<LAYOUT_TYPE>personal</LAYOUT_TYPE>
			<FORCE>
				<LAYOUT>2x2</LAYOUT>
				<CELL>
					<ID>1</ID>
					<FORCE_STATE>auto</FORCE_STATE>
					<FORCE_ID>-1</FORCE_ID>
					<FORCE_NAME/>
					<SOURCE_ID>-1</SOURCE_ID>
				</CELL>
				<CELL>
					<ID>2</ID>
					<FORCE_STATE>auto</FORCE_STATE>
					<FORCE_ID>-1</FORCE_ID>
					<FORCE_NAME/>
					<SOURCE_ID>-1</SOURCE_ID>
				</CELL>
				<CELL>
					<ID>3</ID>
					<FORCE_STATE>auto</FORCE_STATE>
					<FORCE_ID>-1</FORCE_ID>
					<FORCE_NAME/>
					<SOURCE_ID>-1</SOURCE_ID>
				</CELL>
				<CELL>
					<ID>4</ID>
					<FORCE_STATE>auto</FORCE_STATE>
					<FORCE_ID>-1</FORCE_ID>
					<FORCE_NAME/>
					<SOURCE_ID>-1</SOURCE_ID>
				</CELL>
				<CELL>
					<ID>5</ID>
					<FORCE_STATE>auto</FORCE_STATE>
					<FORCE_ID>-1</FORCE_ID>
					<FORCE_NAME/>
					<SOURCE_ID>-1</SOURCE_ID>
				</CELL>
				<CELL>
					<ID>6</ID>
					<FORCE_STATE>auto</FORCE_STATE>
					<FORCE_ID>-1</FORCE_ID>
					<FORCE_NAME/>
					<SOURCE_ID>-1</SOURCE_ID>
				</CELL>
				<CELL>
					<ID>7</ID>
					<FORCE_STATE>auto</FORCE_STATE>
					<FORCE_ID>-1</FORCE_ID>
					<FORCE_NAME/>
					<SOURCE_ID>-1</SOURCE_ID>
				</CELL>
				<CELL>
					<ID>8</ID>
					<FORCE_STATE>auto</FORCE_STATE>
					<FORCE_ID>-1</FORCE_ID>
					<FORCE_NAME/>
					<SOURCE_ID>-1</SOURCE_ID>
				</CELL>
				<CELL>
					<ID>9</ID>
					<FORCE_STATE>auto</FORCE_STATE>
					<FORCE_ID>-1</FORCE_ID>
					<FORCE_NAME/>
					<SOURCE_ID>-1</SOURCE_ID>
				</CELL>
				<CELL>
					<ID>10</ID>
					<FORCE_STATE>auto</FORCE_STATE>
					<FORCE_ID>-1</FORCE_ID>
					<FORCE_NAME/>
					<SOURCE_ID>-1</SOURCE_ID>
				</CELL>
				<CELL>
					<ID>11</ID>
					<FORCE_STATE>auto</FORCE_STATE>
					<FORCE_ID>-1</FORCE_ID>
					<FORCE_NAME/>
					<SOURCE_ID>-1</SOURCE_ID>
				</CELL>
				<CELL>
					<ID>12</ID>
					<FORCE_STATE>auto</FORCE_STATE>
					<FORCE_ID>-1</FORCE_ID>
					<FORCE_NAME/>
					<SOURCE_ID>-1</SOURCE_ID>
				</CELL>
				<CELL>
					<ID>13</ID>
					<FORCE_STATE>auto</FORCE_STATE>
					<FORCE_ID>-1</FORCE_ID>
					<FORCE_NAME/>
					<SOURCE_ID>-1</SOURCE_ID>
				</CELL>
				<CELL>
					<ID>14</ID>
					<FORCE_STATE>auto</FORCE_STATE>
					<FORCE_ID>-1</FORCE_ID>
					<FORCE_NAME/>
					<SOURCE_ID>-1</SOURCE_ID>
				</CELL>
				<CELL>
					<ID>15</ID>
					<FORCE_STATE>auto</FORCE_STATE>
					<FORCE_ID>-1</FORCE_ID>
					<FORCE_NAME/>
					<SOURCE_ID>-1</SOURCE_ID>
				</CELL>
				<CELL>
					<ID>16</ID>
					<FORCE_STATE>auto</FORCE_STATE>
					<FORCE_ID>-1</FORCE_ID>
					<FORCE_NAME/>
					<SOURCE_ID>-1</SOURCE_ID>
				</CELL>
			</FORCE>
		</SET_PARTY_VIDEO_LAYOUT_EX>
	</ACTION>
</TRANS_CONF_1>